README.rst
setup.cfg
setup.py
query_selector/__init__.py
query_selector/example.sql
query_selector/magic.py
query_selector/test.py
query_selector.egg-info/PKG-INFO
query_selector.egg-info/SOURCES.txt
query_selector.egg-info/dependency_links.txt
query_selector.egg-info/requires.txt
query_selector.egg-info/top_level.txt