Metadata-Version: 1.1
Name: query-selector
Version: 0.99.4
Summary: Organize app queries in an annotated SQL file.
Home-page: https://github.com/solidsnack/query-selector
Author: Jason Dusek
Author-email: jason.dusek@gmail.com
License: UNKNOWN
Platform: UNKNOWN
Classifier: Environment :: Console
Classifier: Intended Audience :: Developers
Classifier: License :: OSI Approved :: MIT License
Classifier: Operating System :: Unix
Classifier: Operating System :: POSIX
Classifier: Programming Language :: Python
Classifier: Programming Language :: Python :: 2.6
Classifier: Programming Language :: Python :: 2.7
Classifier: Programming Language :: Python :: 3.5
Classifier: Topic :: Software Development
Classifier: Development Status :: 4 - Beta
